fds/__init__.py
fds/sdk/__init__.py
fds/sdk/StreetAccountNews/__init__.py
fds/sdk/StreetAccountNews/api_client.py
fds/sdk/StreetAccountNews/configuration.py
fds/sdk/StreetAccountNews/exceptions.py
fds/sdk/StreetAccountNews/model_utils.py
fds/sdk/StreetAccountNews/rest.py
fds/sdk/StreetAccountNews/api/__init__.py
fds/sdk/StreetAccountNews/api/filters_api.py
fds/sdk/StreetAccountNews/api/headlines_api.py
fds/sdk/StreetAccountNews/api/views_api.py
fds/sdk/StreetAccountNews/apis/__init__.py
fds/sdk/StreetAccountNews/model/__init__.py
fds/sdk/StreetAccountNews/model/create_or_edit_view_body.py
fds/sdk/StreetAccountNews/model/create_or_edit_view_body_data.py
fds/sdk/StreetAccountNews/model/create_or_edit_view_tickers.py
fds/sdk/StreetAccountNews/model/create_view_response.py
fds/sdk/StreetAccountNews/model/create_view_response_data.py
fds/sdk/StreetAccountNews/model/delete_view_body.py
fds/sdk/StreetAccountNews/model/delete_view_body_data.py
fds/sdk/StreetAccountNews/model/error.py
fds/sdk/StreetAccountNews/model/error_object.py
fds/sdk/StreetAccountNews/model/filter_categories_response.py
fds/sdk/StreetAccountNews/model/filter_categories_response_data.py
fds/sdk/StreetAccountNews/model/filter_regions_response.py
fds/sdk/StreetAccountNews/model/filter_regions_response_data.py
fds/sdk/StreetAccountNews/model/filter_response.py
fds/sdk/StreetAccountNews/model/filter_response_data.py
fds/sdk/StreetAccountNews/model/filter_sectors_response.py
fds/sdk/StreetAccountNews/model/filter_sectors_response_data.py
fds/sdk/StreetAccountNews/model/filter_topic_response.py
fds/sdk/StreetAccountNews/model/filter_topic_response_data.py
fds/sdk/StreetAccountNews/model/filter_watchlists_response.py
fds/sdk/StreetAccountNews/model/filter_watchlists_response_data.py
fds/sdk/StreetAccountNews/model/flattened_filters.py
fds/sdk/StreetAccountNews/model/flattened_filters_categories.py
fds/sdk/StreetAccountNews/model/flattened_filters_categories_object.py
fds_sdk_streetaccountnews-1.3.0.dist-info/licenses/LICENSE
fds_sdk_streetaccountnews-1.3.0.dist-info/METADATA
fds_sdk_streetaccountnews-1.3.0.dist-info/WHEEL
fds_sdk_streetaccountnews-1.3.0.dist-info/top_level.txt
fds_sdk_streetaccountnews-1.3.0.dist-info/RECORD
